LICENSE.txt
MANIFEST.in
README.md
pyproject.toml
setup.cfg
setup.py
pear_ebi/__init__.py
pear_ebi/__main__.py
pear_ebi/_install_helpers.py
pear_ebi/test.py
pear_ebi/tree_emb_parser.py
pear_ebi/tree_set.py
pear_ebi.egg-info/PKG-INFO
pear_ebi.egg-info/SOURCES.txt
pear_ebi.egg-info/dependency_links.txt
pear_ebi.egg-info/entry_points.txt
pear_ebi.egg-info/not-zip-safe
pear_ebi.egg-info/requires.txt
pear_ebi.egg-info/top_level.txt
pear_ebi/calculate_distances/RF_pypy.py
pear_ebi/calculate_distances/__init__.py
pear_ebi/calculate_distances/hashrf.py
pear_ebi/calculate_distances/maple_RF.py
pear_ebi/calculate_distances/tqdist.py
pear_ebi/calculate_distances/linux_bin/HashRF/AUTHORS
pear_ebi/calculate_distances/linux_bin/HashRF/COPYING
pear_ebi/calculate_distances/linux_bin/HashRF/ChangeLog
pear_ebi/calculate_distances/linux_bin/HashRF/INSTALL
pear_ebi/calculate_distances/linux_bin/HashRF/Makefile
pear_ebi/calculate_distances/linux_bin/HashRF/Makefile.am
pear_ebi/calculate_distances/linux_bin/HashRF/Makefile.in
pear_ebi/calculate_distances/linux_bin/HashRF/NEWS
pear_ebi/calculate_distances/linux_bin/HashRF/README
pear_ebi/calculate_distances/linux_bin/HashRF/Random.cpp
pear_ebi/calculate_distances/linux_bin/HashRF/Random.o
pear_ebi/calculate_distances/linux_bin/HashRF/aclocal.m4
pear_ebi/calculate_distances/linux_bin/HashRF/config.h
pear_ebi/calculate_distances/linux_bin/HashRF/config.h.in
pear_ebi/calculate_distances/linux_bin/HashRF/config.hh
pear_ebi/calculate_distances/linux_bin/HashRF/config.hh.in
pear_ebi/calculate_distances/linux_bin/HashRF/config.log
pear_ebi/calculate_distances/linux_bin/HashRF/config.status
pear_ebi/calculate_distances/linux_bin/HashRF/configure
pear_ebi/calculate_distances/linux_bin/HashRF/configure.ac
pear_ebi/calculate_distances/linux_bin/HashRF/configure.lineno
pear_ebi/calculate_distances/linux_bin/HashRF/depcomp
pear_ebi/calculate_distances/linux_bin/HashRF/hash.cc
pear_ebi/calculate_distances/linux_bin/HashRF/hash.hh
pear_ebi/calculate_distances/linux_bin/HashRF/hash.o
pear_ebi/calculate_distances/linux_bin/HashRF/hashfunc.cc
pear_ebi/calculate_distances/linux_bin/HashRF/hashfunc.hh
pear_ebi/calculate_distances/linux_bin/HashRF/hashfunc.o
