Metadata-Version: 2.4
Name: pear_ebi
Version: 1.0.1.6
Summary: Embeds phylogenetic tree distances and produce representations
Home-page: https://github.com/AndreaRubbi/TreeEmbedding
Author: Andrea Rubbi
Author-email: andrea.rubbi.98@gmail.com
License: MIT License
Classifier: Development Status :: 3 - Alpha
Classifier: Programming Language :: Python :: 3.7
Classifier: Programming Language :: Python :: 3.8
Classifier: Programming Language :: Python :: 3.9
License-File: LICENSE.txt
Requires-Dist: numpy<2.0.0
Requires-Dist: pandas<=2.3.3
Requires-Dist: matplotlib>=3.4
Requires-Dist: scikit-learn<=1.6.1
Requires-Dist: rich<=14.2.0
Requires-Dist: pyDRMetrics==0.0.7
Requires-Dist: tqdm<=4.67.1
Requires-Dist: toml==0.10.2
Requires-Dist: kaleido==1.2.0
Requires-Dist: ipykernel==6.17.1
Requires-Dist: ipython==8.6.0
Requires-Dist: ipywidgets==7.7.2
Requires-Dist: jupyter==1.0.0
Requires-Dist: notebook==6.5.6
Requires-Dist: jupyterlab==3.5.0
Requires-Dist: nbconvert==6.4.5
Requires-Dist: pandoc==2.4
Requires-Dist: plotly==5.11.0
Requires-Dist: scipy<=1.13.1
Requires-Dist: Wand==0.6.13
Dynamic: author
Dynamic: author-email
Dynamic: classifier
Dynamic: description
Dynamic: description-content-type
Dynamic: home-page
Dynamic: license
Dynamic: license-file
Dynamic: requires-dist
Dynamic: summary
